data1.csv
setup.py
week9project.py
Hellovivianas9250.egg-info/PKG-INFO
Hellovivianas9250.egg-info/SOURCES.txt
Hellovivianas9250.egg-info/dependency_links.txt
Hellovivianas9250.egg-info/requires.txt
Hellovivianas9250.egg-info/top_level.txt