Metadata-Version: 1.1
Name: Hellovivianas9250
Version: 0.1
Summary: This is my project
Home-page: UNKNOWN
Author: Me
Author-email: UNKNOWN
License: UNKNOWN
Keywords: clusters example
Platform: UNKNOWN
Classifier: License :: OSI Approved :: Python Software Foundation License
